tum_esm_em27_metadata/__init__.py
tum_esm_em27_metadata/interfaces.py
tum_esm_em27_metadata/py.typed
tum_esm_em27_metadata/types.py
tum_esm_em27_metadata-1.0.1.dist-info/WHEEL
tum_esm_em27_metadata-1.0.1.dist-info/METADATA
tum_esm_em27_metadata-1.0.1.dist-info/RECORD
